cfinterface/__init__.py
cfinterface/py.typed
cfinterface/_utils/__init__.py
cfinterface/adapters/__init__.py
cfinterface/adapters/components/__init__.py
cfinterface/adapters/components/repository.py
cfinterface/adapters/components/line/__init__.py
cfinterface/adapters/components/line/repository.py
cfinterface/adapters/reading/__init__.py
cfinterface/adapters/reading/repository.py
cfinterface/adapters/writing/__init__.py
cfinterface/adapters/writing/repository.py
cfinterface/components/__init__.py
cfinterface/components/block.py
cfinterface/components/datetimefield.py
cfinterface/components/defaultblock.py
cfinterface/components/defaultregister.py
cfinterface/components/defaultsection.py
cfinterface/components/field.py
cfinterface/components/floatfield.py
cfinterface/components/integerfield.py
cfinterface/components/line.py
cfinterface/components/literalfield.py
cfinterface/components/register.py
cfinterface/components/section.py
cfinterface/data/__init__.py
cfinterface/data/blockdata.py
cfinterface/data/registerdata.py
cfinterface/data/sectiondata.py
cfinterface/files/__init__.py
cfinterface/files/blockfile.py
cfinterface/files/registerfile.py
cfinterface/files/sectionfile.py
cfinterface/reading/__init__.py
cfinterface/reading/blockreading.py
cfinterface/reading/registerreading.py
cfinterface/reading/sectionreading.py
cfinterface/writing/__init__.py
cfinterface/writing/blockwriting.py
cfinterface/writing/registerwriting.py
cfinterface/writing/sectionwriting.py
cfinterface-1.8.3.dist-info/METADATA
cfinterface-1.8.3.dist-info/WHEEL
cfinterface-1.8.3.dist-info/licenses/LICENSE
cfinterface-1.8.3.dist-info/RECORD
