Metadata-Version: 2.4
Name: cfinterface
Version: 1.8.3
Summary: Interface for handling custom formatted files
Project-URL: Documentation, https://rjmalves.github.io/cfinterface/
Project-URL: Repository, https://github.com/rjmalves/cfinterface/
Author-email: Rogerio Alves <rogerioalves.ee@gmail.com>
License: MIT License
License-File: LICENSE
Classifier: Development Status :: 4 - Beta
Classifier: Intended Audience :: Developers
Classifier: License :: OSI Approved :: MIT License
Classifier: Operating System :: OS Independent
Classifier: Programming Language :: Python :: 3.10
Requires-Python: >=3.10
Requires-Dist: numpy>=2.0.0
Requires-Dist: pandas>=2.2.3
Provides-Extra: dev
Requires-Dist: matplotlib; extra == 'dev'
Requires-Dist: mypy; extra == 'dev'
Requires-Dist: numpydoc; extra == 'dev'
Requires-Dist: plotly; extra == 'dev'
Requires-Dist: pytest; extra == 'dev'
Requires-Dist: pytest-cov; extra == 'dev'
Requires-Dist: ruff; extra == 'dev'
Requires-Dist: sphinx; extra == 'dev'
Requires-Dist: sphinx-gallery; extra == 'dev'
Requires-Dist: sphinx-rtd-theme; extra == 'dev'
